[
 {
  "id": 11,
  "ko": "@c6「캡슐」@c7이 가득 찼을 때…"
 },
 {
  "id": 31,
  "ko": "@c7【아무로】「대, 대단해…」"
 },
 {
  "id": 51,
  "ko": "@c7【샤아】「하, 화력이…… 너무 차이가 나!」"
 },
 {
  "id": 71,
  "ko": "@c7【아무로】「싸우면서 조심할 수 있을 거라고 생각하십니까?」"
 },
 {
  "id": 91,
  "ko": "@c7【켈겔렌 아가씨】「10기 격추…… 인 것 같습니다.」"
 },
 {
  "id": 111,
  "ko": "@c7【아무로】「아무로, ν건담, 출격한다!」"
 },
 {
  "id": 131,
  "ko": "「난투 우주（우주편）」"
 },
 {
  "id": 151,
  "ko": "@c7이 악마 놈…우와아앗!"
 },
 {
  "id": 171,
  "ko": "@c7흥…잘 알고 있잖아, 아무로 군."
 },
 {
  "id": 191,
  "ko": "@c7자네는, 살아남을 수 있겠나?"
 },
 {
  "id": 211,
  "ko": "@c7그래도 전보다는 적어.\\\\n아무로, 너라면 할 수 있어."
 },
 {
  "id": 231,
  "ko": "@c7조작에서 모르는 게 있으면, 메뉴\\\\n의 @c6「조작 설명」@c7을 보면 돼."
 },
 {
  "id": 251,
  "ko": "@c5「태클」@c7은, 적을 넘어뜨릴\\\\n수 있어.\\\\n또, 적의 @c5「격투」@c7를 봉쇄하는 효과도\\\\n있으니까, 많은 적에게 둘러싸였을 때\\\\n@c7사용하면 좋아."
 },
 {
  "id": 271,
  "ko": "@c7그럼, 어떤 공격인지,\\\\n실제로 맞아 보고 확인해 보자."
 },
 {
  "id": 291,
  "ko": "@c7이 배틀부터 60초의 시간 제한이\\\\n붙어. 시간 내에 승부가 나지 않으면\\\\n무승부가 되니까."
 },
 {
  "id": 311,
  "ko": "@c7건방진 짓을…"
 },
 {
  "id": 331,
  "ko": "@c7과연, 좋은 작전이군."
 },
 {
  "id": 351,
  "ko": "@c7우와아아아아앗!"
 },
 {
  "id": 371,
  "ko": "@c7그럼, 시작해 볼까!"
 },
 {
  "id": 391,
  "ko": "@c7마지막 1기가 출격했습니다!"
 },
 {
  "id": 411,
  "ko": "@c71대1로 대결해서 이겨 나갑니다.\\\\n먼저 5기를 쓰러뜨린 쪽이 승리."
 },
 {
  "id": 431,
  "ko": "@c7앞으로 10초!"
 },
 {
  "id": 451,
  "ko": "@c7슬레거, 나간다!"
 },
 {
  "id": 471,
  "ko": "@c7볼 이외를 쓰러뜨리면 안 돼!"
 },
 {
  "id": 491,
  "ko": "@c7받아라ー!\\\\n메싸아아아아아아아아앗!"
 },
 {
  "id": 511,
  "ko": ")\u0000\u0000\u0000\u0000\u0000\u0006\u0000"
 },
 {
  "id": 531,
  "ko": "\u0004\u0000\u0000\u0000\u0000\u0000@\u0003\u0000\u0000\u000b\u0000\b\u0000"
 },
 {
  "id": 551,
  "ko": "@c7만약,\\\\n내 곁으로 돌아올 뜻이 있다면……"
 },
 {
  "id": 571,
  "ko": "@c0나는 배틀에서\\\\n싸우는 법을 가르쳐 줄게.\\n함께 힘내자."
 },
 {
  "id": 591,
  "ko": "@c7화살표가 가리키는 @c6「유닛」@c7\\\\n에 @c6「커서」@c7를 겹쳐서\\\\n@b4를 눌러."
 },
 {
  "id": 611,
  "ko": "@c7화살표의 적에게 @c6「유닛」@c7\\\\n을 겹치는 거야."
 },
 {
  "id": 631,
  "ko": "@c7이 @c6이지스 건담@c7은 요주의입니다.\\\\n반드시 여럿이서 공격을 가합시다"
 },
 {
  "id": 651,
  "ko": "@c7다수의 @c6「유닛」@c7으로 공격하는 편이,\\\\n배틀을 유리하게 진행할 수 있어."
 },
 {
  "id": 671,
  "ko": "(\u0000\u0005\u0000\u0000\u0000\u0000\u0000"
 },
 {
  "id": 691,
  "ko": "\u0004\u0000\u0000\u0000\u0000\u0000ﾈ\n\u0000\u0000\u000b\u0000\b\u0000"
 },
 {
  "id": 711,
  "ko": "@c0그래서 어른은 싫어.\\n그 생각,\\n뜯어고쳐 주마!"
 },
 {
  "id": 731,
  "ko": "@c0역시 아무로 씨를\\n이긴 사람이야.\\n내가 이길 리\\n없겠네요…"
 },
 {
  "id": 751,
  "ko": "@c7화살표의 @c6「유닛」@c7\\\\n을 잡아 줘."
 },
 {
  "id": 771,
  "ko": "\u0004\u0000\u0000\u0000\u0000\u0000ｼ\u0012\u0000\u0000\u000b\u0000\b\u0000"
 },
 {
  "id": 791,
  "ko": "@c0내 이름은 포우.\\n너희들은 나를\\n괴롭히러 왔어…\\n모두 타 버려라!"
 },
 {
  "id": 811,
  "ko": "@c7그럼, 나머지는 자유롭게 움직여서 적을\\\\n쓰러뜨려 버려."
 },
 {
  "id": 831,
  "ko": "@c7화살표가 붙어 있는 @c6「유닛」@c7에 겹쳐서\\\\n눌러 보는 거야."
 },
 {
  "id": 851,
  "ko": "@c0너희들은\\n방해가 될 뿐이야.\\n우리의 힘을\\n그 눈에 똑똑히 새겨라!"
 },
 {
  "id": 871,
  "ko": "info/dat/sub_t10.dat"
 },
 {
  "id": 891,
  "ko": "@c7이렇게, @c6「링크」@c7하면 @c6「유닛」@c7이 지나가지\\\\n않은 곳도 @c6「진지」@c7가 되는 거야."
 },
 {
  "id": 911,
  "ko": "@c7이걸 @c6「링크 데미지」@c7라고 해.\\\\n적에게 강한 @c6「유닛」@c7이 있을 때는,\\\\n@c6「링크 데미지」@c7를 준 다음\\\\n배틀하면 좋아."
 },
 {
  "id": 931,
  "ko": "@c0이, 대체 무슨 일이?!\\n내가 모르는\\n전술이라도\\n있었던 건가?"
 },
 {
  "id": 951,
  "ko": "@c0하지만,\\n더 이상은 못 하게 하겠다!"
 },
 {
  "id": 971,
  "ko": "@c7강적은, 무리하게 배틀로 쓰러뜨리지 않아도\\\\n적의 @c4「Ｇ폴리스」@c7를 @c6「점령」@c7하거나,\\\\n@c6「진지」@c7를 차지해서 이기는 것도 방법이야."
 },
 {
  "id": 991,
  "ko": "@c7델타「…!」"
 },
 {
  "id": 1011,
  "ko": "@c7【샤아】「성급하군. 결정 대사 정도는,\\\\n끝까지 말하게 해 줬으면 좋겠는데‥‥."
 },
 {
  "id": 1031,
  "ko": "@c7【아무로】「큰일이야, 빨간 진지가 너무 많아.\\\\n최대한, 빨간 진지를 파랑으로 바꿔야‥‥」"
 },
 {
  "id": 1051,
  "ko": "@c7【마류】「그래, 맞아.」"
 },
 {
  "id": 1071,
  "ko": "@c7【마류】「기체마다 각각, 약한 지형이 있어.\\\\n약한 지형에서는, 평소 성능을 낼 수 없어.」"
 },
 {
  "id": 1091,
  "ko": "@c7【발트펠트】「싸울 수밖에 없겠지, 서로 적인 이상‥‥\\\\n어느 한쪽이 멸망할 때까지 말이야!」"
 }
]