[
 {"id": 7, "ko": "@bb로그표시"},
 {"id": 19, "ko": "하시겠습니까?"},
 {"id": 31, "ko": "재시도"},
 {"id": 43, "ko": "3D 카메라"},
 {"id": 56, "ko": "번호"},
 {"id": 68, "ko": "유닛을 제거할 수 없습니다!"},
 {"id": 80, "ko": "미션 플레이!"},
 {"id": 92, "ko": "@c6어려움"},
 {"id": 104, "ko": "（기록）합니다"},
 {"id": 116, "ko": "취소"},
 {"id": 128, "ko": "미사일에레카"},
 {"id": 140, "ko": "마테리얼"},
 {"id": 152, "ko": "이동코스트참조처"},
 {"id": 164, "ko": "맵병기공격범위X1"},
 {"id": 176, "ko": "자진녹지화"},
 {"id": 188, "ko": "유닛"},
 {"id": 200, "ko": "하이드룰"},
 {"id": 212, "ko": "우주산맥코스트"},
 {"id": 224, "ko": "최강유닛"},
 {"id": 238, "ko": "적>영>거"},
 {"id": 250, "ko": "HP5할회복"},
 {"id": 262, "ko": "1/3퍼센트"},
 {"id": 274, "ko": "캐릭터명"},
 {"id": 286, "ko": "공격유닛행동우선순위"},
 {"id": 298, "ko": "%s데이터"},
 {"id": 310, "ko": "배치파일코멘트"},
 {"id": 322, "ko": "진지쟁탈룰"},
 {"id": 334, "ko": "캐릭터RED2"},
 {"id": 346, "ko": "링크대미지율과묶음대미지율"},
 {"id": 358, "ko": "AB생존회복치"},
 {"id": 370, "ko": "문클리어"},
 {"id": 382, "ko": "육적응랭크"},
 {"id": 394, "ko": "최대저축이동력"},
 {"id": 406, "ko": "@s0@c7속성@i608은 움직일 수 없다!"},
 {"id": 418, "ko": "@c7적의 거점병기 범위"},
 {"id": 430, "ko": "랜덤거리"},
 {"id": 442, "ko": "PB대전데모용지상맵"},
 {"id": 454, "ko": "@c7가샤폴리스를 점령했다!!"},
 {"id": 466, "ko": "@c78DAY 동안 결판이 나지 않았다!!"},
 {"id": 478, "ko": "@c66DAY@c7 동안 승부를 내라!"},
 {"id": 490, "ko": "@s0다시 한번 도전하시겠습니까?"},
 {"id": 502, "ko": "@c7이동합니다"},
 {"id": 514, "ko": "@c7포격이 빗나갔다!"},
 {"id": 526, "ko": "싸우고 싶은 너에게!"},
 {"id": 539, "ko": "거점쟁탈전"},
 {"id": 551, "ko": "변화하는전장"},
 {"id": 563, "ko": "ㄱㄴㄷㄹㅁㅂㅅㅇㅈㅊㅋㅌㅍㅎㄲㄸㅃㅆㅉㅏㅑㅓㅕㅗㅛㅜㅠㅡㅣㅐㅔㅒㅖㅘㅙㅚㅝㅞㅟㅢ　　　　　　　　　　　　　　　　　　　　　　　　　　　　　　　　　　　　　　　　　　　　　　　　　　"},
 {"id": 575, "ko": "이상（０）입니다。"},
 {"id": 587, "ko": "@c7저장했습니다."}
]
