[
 {
  "id": 6,
  "jp": "@b1スクロール",
  "budget": 13,
  "occ": 1
 },
 {
  "id": 18,
  "jp": "ＳＤガンダムのデータがこわれています。",
  "budget": 38,
  "occ": 1
 },
 {
  "id": 30,
  "jp": "ミッション|選択(せんたく)へ|戻(もど)る",
  "budget": 38,
  "occ": 1
 },
 {
  "id": 42,
  "jp": "２Ｄカメラ",
  "budget": 10,
  "occ": 1
 },
 {
  "id": 55,
  "jp": "カプセルボックス",
  "budget": 16,
  "occ": 2
 },
 {
  "id": 67,
  "jp": "カプセル|編集(へんしゅう)を|終(お)わります",
  "budget": 42,
  "occ": 1
 },
 {
  "id": 79,
  "jp": "|確認(かくにん)できます",
  "budget": 23,
  "occ": 1
 },
 {
  "id": 91,
  "jp": "@c5ふつう",
  "budget": 9,
  "occ": 1
 },
 {
  "id": 103,
  "jp": "|選択(せんたく)できます",
  "budget": 23,
  "occ": 1
 },
 {
  "id": 115,
  "jp": "このユニットはまだＧＥＴしていません！",
  "budget": 38,
  "occ": 1
 },
 {
  "id": 127,
  "jp": "プチモビルスーツ",
  "budget": 16,
  "occ": 1
 },
 {
  "id": 139,
  "jp": "深海コスト",
  "budget": 10,
  "occ": 3
 },
 {
  "id": 151,
  "jp": "勢力圏内ユニット回復",
  "budget": 20,
  "occ": 1
 },
 {
  "id": 163,
  "jp": "マップ兵器攻撃範囲X0",
  "budget": 20,
  "occ": 1
 },
 {
  "id": 175,
  "jp": "自陣整地",
  "budget": 8,
  "occ": 1
 },
 {
  "id": 187,
  "jp": "対象なし",
  "budget": 8,
  "occ": 1
 },
 {
  "id": 199,
  "jp": "制圧度が低い",
  "budget": 12,
  "occ": 1
 },
 {
  "id": 211,
  "jp": "クレーターコスト",
  "budget": 16,
  "occ": 1
 },
 {
  "id": 223,
  "jp": "ランダム",
  "budget": 8,
  "occ": 3
 },
 {
  "id": 237,
  "jp": "3機で守る",
  "budget": 9,
  "occ": 1
 },
 {
  "id": 249,
  "jp": "ＨＰ４割で回復",
  "budget": 14,
  "occ": 1
 },
 {
  "id": 261,
  "jp": "１／４パーセント",
  "budget": 16,
  "occ": 1
 },
 {
  "id": 273,
  "jp": "バトルしない",
  "budget": 12,
  "occ": 1
 },
 {
  "id": 285,
  "jp": "守備ユニット迎撃設定",
  "budget": 20,
  "occ": 1
 },
 {
  "id": 297,
  "jp": "バトルアイテム判断",
  "budget": 18,
  "occ": 1
 },
 {
  "id": 309,
  "jp": "配置ファイル名",
  "budget": 14,
  "occ": 1
 },
 {
  "id": 321,
  "jp": "制限時間",
  "budget": 8,
  "occ": 1
 },
 {
  "id": 333,
  "jp": "思考レベルRED1",
  "budget": 14,
  "occ": 1
 },
 {
  "id": 345,
  "jp": "ユニット維持費倍率",
  "budget": 18,
  "occ": 1
 },
 {
  "id": 357,
  "jp": "グリッドカラー（宇宙）",
  "budget": 22,
  "occ": 1
 },
 {
  "id": 369,
  "jp": "カプセル取得確率",
  "budget": 16,
  "occ": 1
 },
 {
  "id": 381,
  "jp": "宇宙適応ランク",
  "budget": 14,
  "occ": 1
 },
 {
  "id": 393,
  "jp": "砲撃死角距離",
  "budget": 12,
  "occ": 1
 },
 {
  "id": 405,
  "jp": "シナリオ用デック",
  "budget": 16,
  "occ": 1
 },
 {
  "id": 417,
  "jp": "%s　@c5(パー)",
  "budget": 13,
  "occ": 1
 },
 {
  "id": 429,
  "jp": "ランダムベース",
  "budget": 14,
  "occ": 1
 },
 {
  "id": 441,
  "jp": "ランダムマップD",
  "budget": 15,
  "occ": 1
 },
 {
  "id": 453,
  "jp": "@c5「カプセル|編集(へんしゅう)」@c7ができるようになった！",
  "budget": 57,
  "occ": 1
 },
 {
  "id": 465,
  "jp": "@c7|７ＤＡＹ(なのか)で|決着(けっちゃく)がつかなかった！！",
  "budget": 57,
  "occ": 1
 },
 {
  "id": 477,
  "jp": "@c6|５ＤＡＹ(いつか)@c7の|間(あいだ)に|勝負(しょうぶ)を|決(き)めろ!",
  "budget": 67,
  "occ": 1
 },
 {
  "id": 489,
  "jp": "@c6|一歩(いっぽ)も|動(うご)けない！",
  "budget": 35,
  "occ": 1
 },
 {
  "id": 501,
  "jp": "@c7@c6|味方(みかた)ユニットをおし|出(だ)します",
  "budget": 46,
  "occ": 2
 },
 {
  "id": 513,
  "jp": "ゲームを|終了(しゅうりょう)しますか？",
  "budget": 37,
  "occ": 4
 },
 {
  "id": 525,
  "jp": "|全(ぜん)５ミッション",
  "budget": 21,
  "occ": 1
 },
 {
  "id": 538,
  "jp": "水中戦と水陸ユニット",
  "budget": 20,
  "occ": 1
 },
 {
  "id": 550,
  "jp": "Ｇポリス",
  "budget": 8,
  "occ": 1
 },
 {
  "id": 562,
  "jp": "ゲームヘルプ",
  "budget": 12,
  "occ": 1
 },
 {
  "id": 574,
  "jp": "|不明(ふめい)なエラーが|発生(はっせい)しました。",
  "budget": 48,
  "occ": 1
 },
 {
  "id": 586,
  "jp": "さわらないでください。",
  "budget": 22,
  "occ": 7
 }
]